{
  "fork_families": [
    {
      "forks": [],
      "root": {
        "created_at": "2025-08-18T14:50:50Z",
        "description": "A Solana Chess Smart Contract is a Solana program (usually built with Rust + Anchor) that manages the rules, moves, and game state of a chess match on-chain.",
        "forks_count": 0,
        "full_name": "0xRustPro/solana-chess-smart-contract",
        "html_url": "https://github.com/0xRustPro/solana-chess-smart-contract",
        "is_fork": false,
        "language": "Rust",
        "last_checked": "2025-12-30T07:02:12.900884Z",
        "name": "solana-chess-smart-contract",
        "owner": "0xRustPro",
        "parent": null,
        "source": null,
        "stars": 1,
        "updated_at": "2025-10-08T08:05:20Z"
      }
    }
  ],
  "last_updated": "2025-12-30T16:57:34.023753Z",
  "orphaned_forks": [],
  "repo_name": "solana-chess-smart-contract",
  "total_repos": 1
}