{
  "fork_families": [
    {
      "forks": [],
      "root": {
        "created_at": "2025-08-18T14:50:22Z",
        "description": "A Solana Poker Casino Game is an online casino-style poker game built on the Solana blockchain, where players use crypto (like SOL or SPL tokens) instead of fiat money.",
        "forks_count": 68,
        "full_name": "0xRustPro/solana-poker-casino-game",
        "html_url": "https://github.com/0xRustPro/solana-poker-casino-game",
        "is_fork": false,
        "language": "TypeScript",
        "last_checked": "2025-12-30T07:02:43.206228Z",
        "name": "solana-poker-casino-game",
        "owner": "0xRustPro",
        "parent": null,
        "source": null,
        "stars": 73,
        "updated_at": "2025-12-21T18:46:37Z"
      }
    }
  ],
  "last_updated": "2025-12-30T16:57:34.027757Z",
  "orphaned_forks": [],
  "repo_name": "solana-poker-casino-game",
  "total_repos": 1
}