{
  "fork_families": [
    {
      "forks": [],
      "root": {
        "created_at": "2023-02-25T04:46:33Z",
        "description": "A fully on-chain trading card game. There will be elves, wizards & shit. Drama and broken friendships also.",
        "forks_count": 44,
        "full_name": "0xFableOrg/0xFable",
        "html_url": "https://github.com/0xFableOrg/0xFable",
        "is_fork": false,
        "language": "TypeScript",
        "last_checked": "2025-12-30T06:20:02.234635Z",
        "name": "0xFable",
        "owner": "0xFableOrg",
        "parent": null,
        "source": null,
        "stars": 106,
        "updated_at": "2025-12-08T13:59:47Z"
      }
    }
  ],
  "last_updated": "2025-12-30T16:57:33.699881Z",
  "orphaned_forks": [],
  "repo_name": "0xFable",
  "total_repos": 1
}