{
  "fork_families": [
    {
      "forks": [],
      "root": {
        "created_at": "2021-12-13T02:55:39Z",
        "description": "Projecto of buildspace in where we have to create an NFT ",
        "forks_count": 1,
        "full_name": "0bkevin/buildspaceNFT",
        "html_url": "https://github.com/0bkevin/buildspaceNFT",
        "is_fork": false,
        "language": "JavaScript",
        "last_checked": "2025-12-30T05:25:35.525851Z",
        "name": "buildspaceNFT",
        "owner": "0bkevin",
        "parent": null,
        "source": null,
        "stars": 0,
        "updated_at": "2021-12-13T02:59:36Z"
      }
    }
  ],
  "last_updated": "2025-12-30T05:47:58.290866Z",
  "orphaned_forks": [],
  "repo_name": "buildspaceNFT",
  "total_repos": 1
}