{
  "fork_families": [
    {
      "forks": [],
      "root": {
        "created_at": "2021-09-23T09:09:56Z",
        "description": "Examples of how Starknet Hardhat plugin can be used.",
        "forks_count": 28,
        "full_name": "0xSpaceShard/starknet-hardhat-example",
        "html_url": "https://github.com/0xSpaceShard/starknet-hardhat-example",
        "is_fork": false,
        "language": "TypeScript",
        "last_checked": "2025-12-30T07:08:42.115794Z",
        "name": "starknet-hardhat-example",
        "owner": "0xSpaceShard",
        "parent": null,
        "source": null,
        "stars": 89,
        "updated_at": "2025-02-12T18:01:50Z"
      }
    }
  ],
  "last_updated": "2025-12-30T16:57:34.072213Z",
  "orphaned_forks": [],
  "repo_name": "starknet-hardhat-example",
  "total_repos": 1
}