{
  "fork_families": [
    {
      "forks": [],
      "root": {
        "created_at": null,
        "description": null,
        "forks_count": 0,
        "full_name": "0xJohnnie/stardust",
        "html_url": "https://github.com/0xJohnnie/stardust",
        "is_fork": false,
        "language": null,
        "last_checked": "2025-12-30T06:28:28.780693Z",
        "name": "stardust",
        "owner": "0xJohnnie",
        "parent": null,
        "source": null,
        "stars": 0,
        "updated_at": null
      }
    }
  ],
  "last_updated": "2025-12-30T16:57:33.767189Z",
  "orphaned_forks": [],
  "repo_name": "stardust",
  "total_repos": 1
}