{
  "fork_families": [
    {
      "forks": [],
      "root": {
        "created_at": "2024-12-17T18:02:44Z",
        "description": "Miden tutorials for a smooth onboarding",
        "forks_count": 9,
        "full_name": "0xMiden/miden-tutorials",
        "html_url": "https://github.com/0xMiden/miden-tutorials",
        "is_fork": false,
        "language": "Rust",
        "last_checked": "2025-12-30T06:37:20.261944Z",
        "name": "miden-tutorials",
        "owner": "0xMiden",
        "parent": null,
        "source": null,
        "stars": 15,
        "updated_at": "2025-12-15T06:08:32Z"
      }
    },
    {
      "forks": [],
      "root": {
        "created_at": "2024-12-17T18:02:44Z",
        "description": "Miden tutorials for a smooth onboarding",
        "forks_count": 9,
        "full_name": "0xPolygonMiden/miden-tutorials",
        "html_url": "https://github.com/0xMiden/miden-tutorials",
        "is_fork": false,
        "language": "Rust",
        "last_checked": "2025-12-30T06:53:13.426510Z",
        "name": "miden-tutorials",
        "owner": "0xMiden",
        "parent": null,
        "source": null,
        "stars": 15,
        "updated_at": "2025-12-15T06:08:32Z"
      }
    }
  ],
  "last_updated": "2025-12-30T16:57:33.836368Z",
  "orphaned_forks": [],
  "repo_name": "miden-tutorials",
  "total_repos": 2
}