{
  "fork_families": [
    {
      "forks": [],
      "root": {
        "created_at": "2022-12-03T19:20:49Z",
        "description": "an NFT project on Mina Protocol",
        "forks_count": 0,
        "full_name": "0xinit/minaworld",
        "html_url": "https://github.com/0xinit/minaworld",
        "is_fork": false,
        "language": "TypeScript",
        "last_checked": "2025-12-30T07:54:47.689463Z",
        "name": "minaworld",
        "owner": "0xinit",
        "parent": null,
        "source": null,
        "stars": 0,
        "updated_at": "2022-12-03T19:21:35Z"
      }
    }
  ],
  "last_updated": "2025-12-30T16:57:34.414834Z",
  "orphaned_forks": [],
  "repo_name": "minaworld",
  "total_repos": 1
}