{
  "fork_families": [
    {
      "forks": [],
      "root": {
        "created_at": "2025-03-01T03:50:00Z",
        "description": "Pell dvs application template which based on pellapp-sdk",
        "forks_count": 1,
        "full_name": "0xPellNetwork/dvs-template",
        "html_url": "https://github.com/0xPellNetwork/dvs-template",
        "is_fork": false,
        "language": "Shell",
        "last_checked": "2025-12-30T06:45:37.403100Z",
        "name": "dvs-template",
        "owner": "0xPellNetwork",
        "parent": null,
        "source": null,
        "stars": 1,
        "updated_at": "2025-04-18T16:39:45Z"
      }
    }
  ],
  "last_updated": "2025-12-30T16:57:33.902732Z",
  "orphaned_forks": [],
  "repo_name": "dvs-template",
  "total_repos": 1
}