{
  "fork_families": [
    {
      "forks": [],
      "root": {
        "created_at": "2025-01-17T04:46:29Z",
        "description": "基於區塊鏈技術的「證書生成/查詢網站」，通過不可篡改的數位證書，為每件商品提供唯一的數位身份，實現商品來源及真偽的有效驗證",
        "forks_count": 0,
        "full_name": "109213054/authentichain",
        "html_url": "https://github.com/109213054/authentichain",
        "is_fork": false,
        "language": "JavaScript",
        "last_checked": "2025-12-30T08:41:49.451701Z",
        "name": "authentichain",
        "owner": "109213054",
        "parent": null,
        "source": null,
        "stars": 0,
        "updated_at": "2025-03-31T07:45:23Z"
      }
    }
  ],
  "last_updated": "2025-12-30T16:57:34.791917Z",
  "orphaned_forks": [],
  "repo_name": "authentichain",
  "total_repos": 1
}