{
  "fork_families": [
    {
      "forks": [],
      "root": {
        "created_at": "2022-08-19T20:40:11Z",
        "description": "Algorand Mass Arc19 Asset Minter",
        "forks_count": 0,
        "full_name": "1fatalix1/arc19-minter",
        "html_url": "https://github.com/1fatalix1/arc19-minter",
        "is_fork": false,
        "language": "JavaScript",
        "last_checked": "2025-12-30T08:59:49.368531Z",
        "name": "arc19-minter",
        "owner": "1fatalix1",
        "parent": null,
        "source": null,
        "stars": 4,
        "updated_at": "2025-02-13T18:28:08Z"
      }
    }
  ],
  "last_updated": "2025-12-30T16:57:34.934203Z",
  "orphaned_forks": [],
  "repo_name": "arc19-minter",
  "total_repos": 1
}