{
  "fork_families": [
    {
      "forks": [],
      "root": {
        "created_at": "2023-08-06T19:49:25Z",
        "description": null,
        "forks_count": 0,
        "full_name": "10ambear/PatrickCollinsCourse",
        "html_url": "https://github.com/10ambear/PatrickCollinsCourse",
        "is_fork": false,
        "language": "Solidity",
        "last_checked": "2025-12-30T08:42:04.090510Z",
        "name": "PatrickCollinsCourse",
        "owner": "10ambear",
        "parent": null,
        "source": null,
        "stars": 0,
        "updated_at": "2023-08-06T19:49:34Z"
      }
    }
  ],
  "last_updated": "2025-12-30T16:57:34.794326Z",
  "orphaned_forks": [],
  "repo_name": "PatrickCollinsCourse",
  "total_repos": 1
}