{
  "fork_families": [
    {
      "forks": [],
      "root": {
        "created_at": null,
        "description": null,
        "forks_count": 0,
        "full_name": "0LNetworkCommunity/aptos-core",
        "html_url": "https://github.com/0LNetworkCommunity/aptos-core",
        "is_fork": false,
        "language": null,
        "last_checked": "2025-12-30T05:24:27.817281Z",
        "name": "aptos-core",
        "owner": "0LNetworkCommunity",
        "parent": null,
        "source": null,
        "stars": 0,
        "updated_at": null
      }
    }
  ],
  "last_updated": "2025-12-30T05:47:58.281585Z",
  "orphaned_forks": [],
  "repo_name": "aptos-core",
  "total_repos": 1
}