{
  "fork_families": [
    {
      "forks": [],
      "root": {
        "created_at": "2024-02-10T00:34:04Z",
        "description": "EVM Calldata Zip, aka czip",
        "forks_count": 5,
        "full_name": "0xsequence/czip",
        "html_url": "https://github.com/0xsequence/czip",
        "is_fork": false,
        "language": "Go",
        "last_checked": "2025-12-30T08:22:25.142290Z",
        "name": "czip",
        "owner": "0xsequence",
        "parent": null,
        "source": null,
        "stars": 101,
        "updated_at": "2025-11-14T06:57:16Z"
      }
    }
  ],
  "last_updated": "2025-12-30T16:57:34.650826Z",
  "orphaned_forks": [],
  "repo_name": "czip",
  "total_repos": 1
}