{
  "fork_families": [
    {
      "forks": [],
      "root": {
        "created_at": "2022-06-17T02:59:26Z",
        "description": null,
        "forks_count": 0,
        "full_name": "0xlax/switchboardv2-go",
        "html_url": "https://github.com/0xlax/switchboardv2-go",
        "is_fork": false,
        "language": "Go",
        "last_checked": "2025-12-30T08:02:11.724296Z",
        "name": "switchboardv2-go",
        "owner": "0xlax",
        "parent": null,
        "source": null,
        "stars": 0,
        "updated_at": "2022-07-21T15:17:06Z"
      }
    }
  ],
  "last_updated": "2025-12-30T16:57:34.470223Z",
  "orphaned_forks": [],
  "repo_name": "switchboardv2-go",
  "total_repos": 1
}