{
  "fork_families": [
    {
      "forks": [],
      "root": {
        "created_at": "2025-06-21T01:06:52Z",
        "description": "DeFi lending by introducing hybrid collateralization - combining on-chain assets with off-chain credit guarantees",
        "forks_count": 1,
        "full_name": "0xgeorgemathew/credit-shaft-contracts",
        "html_url": "https://github.com/0xgeorgemathew/credit-shaft-contracts",
        "is_fork": false,
        "language": "Solidity",
        "last_checked": "2025-12-30T07:48:04.075441Z",
        "name": "credit-shaft-contracts",
        "owner": "0xgeorgemathew",
        "parent": null,
        "source": null,
        "stars": 0,
        "updated_at": "2025-11-03T16:57:06Z"
      }
    }
  ],
  "last_updated": "2025-12-30T16:57:34.363160Z",
  "orphaned_forks": [],
  "repo_name": "credit-shaft-contracts",
  "total_repos": 1
}