{
  "fork_families": [
    {
      "forks": [],
      "root": {
        "created_at": "2022-08-16T15:04:47Z",
        "description": "An example to cross chain ERC20 token.",
        "forks_count": 0,
        "full_name": "0fatih/crosschain-erc20",
        "html_url": "https://github.com/0fatih/crosschain-erc20",
        "is_fork": false,
        "language": "JavaScript",
        "last_checked": "2025-12-30T05:27:20.915270Z",
        "name": "crosschain-erc20",
        "owner": "0fatih",
        "parent": null,
        "source": null,
        "stars": 4,
        "updated_at": "2023-10-05T15:21:06Z"
      }
    }
  ],
  "last_updated": "2025-12-30T05:47:58.310790Z",
  "orphaned_forks": [],
  "repo_name": "crosschain-erc20",
  "total_repos": 1
}