{
  "fork_families": [
    {
      "forks": [],
      "root": {
        "created_at": "2022-11-15T22:59:34Z",
        "description": null,
        "forks_count": 0,
        "full_name": "0xDAEF0F/nft_metadata_monorepo",
        "html_url": "https://github.com/0xDAEF0F/nft_metadata_monorepo",
        "is_fork": false,
        "language": "TypeScript",
        "last_checked": "2025-12-30T06:12:36.506250Z",
        "name": "nft_metadata_monorepo",
        "owner": "0xDAEF0F",
        "parent": null,
        "source": null,
        "stars": 1,
        "updated_at": "2023-10-03T02:28:36Z"
      }
    }
  ],
  "last_updated": "2025-12-30T16:57:33.643032Z",
  "orphaned_forks": [],
  "repo_name": "nft_metadata_monorepo",
  "total_repos": 1
}