{
  "fork_families": [
    {
      "forks": [],
      "root": {
        "created_at": "2022-10-23T17:46:41Z",
        "description": null,
        "forks_count": 0,
        "full_name": "0xkarmacoma/foundry-huff-playground",
        "html_url": "https://github.com/0xkarmacoma/foundry-huff-playground",
        "is_fork": false,
        "language": "Solidity",
        "last_checked": "2025-12-30T07:58:07.380418Z",
        "name": "foundry-huff-playground",
        "owner": "0xkarmacoma",
        "parent": null,
        "source": null,
        "stars": 3,
        "updated_at": "2022-10-27T04:43:13Z"
      }
    }
  ],
  "last_updated": "2025-12-30T16:57:34.440442Z",
  "orphaned_forks": [],
  "repo_name": "foundry-huff-playground",
  "total_repos": 1
}