{
  "fork_families": [
    {
      "forks": [],
      "root": {
        "created_at": "2024-12-07T16:28:15Z",
        "description": null,
        "forks_count": 0,
        "full_name": "0xsharaf/Cattie_nft",
        "html_url": "https://github.com/0xsharaf/Cattie_nft",
        "is_fork": false,
        "language": "Solidity",
        "last_checked": "2025-12-30T08:25:55.660605Z",
        "name": "Cattie_nft",
        "owner": "0xsharaf",
        "parent": null,
        "source": null,
        "stars": 0,
        "updated_at": "2024-12-07T16:43:20Z"
      }
    }
  ],
  "last_updated": "2025-12-30T16:57:34.673951Z",
  "orphaned_forks": [],
  "repo_name": "Cattie_nft",
  "total_repos": 1
}