{
  "fork_families": [
    {
      "forks": [],
      "root": {
        "created_at": "2024-05-17T00:24:51Z",
        "description": "my solutions to Starknet Basecamp 9 - Counter Workshop",
        "forks_count": 2,
        "full_name": "0xKubitus/basecamp9-counter-workshop",
        "html_url": "https://github.com/0xKubitus/basecamp9-counter-workshop",
        "is_fork": false,
        "language": "TypeScript",
        "last_checked": "2025-12-30T06:32:10.193883Z",
        "name": "basecamp9-counter-workshop",
        "owner": "0xKubitus",
        "parent": null,
        "source": null,
        "stars": 0,
        "updated_at": "2024-05-17T00:52:04Z"
      }
    }
  ],
  "last_updated": "2025-12-30T16:57:33.796087Z",
  "orphaned_forks": [],
  "repo_name": "basecamp9-counter-workshop",
  "total_repos": 1
}