{
  "fork_families": [
    {
      "forks": [],
      "root": {
        "created_at": "2019-04-13T00:22:04Z",
        "description": null,
        "forks_count": 0,
        "full_name": "0xywzx/eth_check-in_proto",
        "html_url": "https://github.com/0xywzx/eth_check-in_proto",
        "is_fork": false,
        "language": "JavaScript",
        "last_checked": "2025-12-30T08:37:51.415985Z",
        "name": "eth_check-in_proto",
        "owner": "0xywzx",
        "parent": null,
        "source": null,
        "stars": 0,
        "updated_at": "2019-08-09T02:11:03Z"
      }
    }
  ],
  "last_updated": "2025-12-30T16:57:34.756662Z",
  "orphaned_forks": [],
  "repo_name": "eth_check-in_proto",
  "total_repos": 1
}