{
  "fork_families": [],
  "last_updated": "2025-12-30T16:57:33.741227Z",
  "orphaned_forks": [
    {
      "created_at": "2021-06-19T13:45:28Z",
      "description": "Monorepo for the Ethereum VM TypeScript Implementation",
      "forks_count": 0,
      "full_name": "0xHashstack/ethereumjs-vm",
      "html_url": "https://github.com/0xHashstack/ethereumjs-vm",
      "is_fork": true,
      "language": null,
      "last_checked": "2025-12-30T06:25:04.690923Z",
      "name": "ethereumjs-vm",
      "owner": "0xHashstack",
      "parent": "Max-Takahashi9/ethereumjs-vm",
      "source": "ethereumjs/ethereumjs-monorepo",
      "stars": 0,
      "updated_at": "2021-06-19T13:45:29Z"
    }
  ],
  "repo_name": "ethereumjs-vm",
  "total_repos": 1
}